qcn/__init__.py
qcn/cli.py
qcn/config.py
qcn/git_utils.py
qcn/storage.py
qcn/validators.py
qcn-0.1.0.dist-info/licenses/LICENSE
qcn-0.1.0.dist-info/METADATA
qcn-0.1.0.dist-info/WHEEL
qcn-0.1.0.dist-info/entry_points.txt
qcn-0.1.0.dist-info/top_level.txt
qcn-0.1.0.dist-info/RECORD
