Metadata-Version: 2.4
Name: qcn
Version: 0.1.0
Summary: Quick Commit Note - interactive commit message CLI
Requires-Python: >=3.8
License-File: LICENSE
Requires-Dist: click>=8.0
Requires-Dist: toml>=0.10
Dynamic: license-file
Dynamic: requires-dist
Dynamic: requires-python
Dynamic: summary
